README.md
setup.py
bahnbusiness/__init__.py
bahnbusiness/__main__.py
bahnbusiness/bahnapi.py
bahnbusiness/journey.py
bahnbusiness.egg-info/PKG-INFO
bahnbusiness.egg-info/SOURCES.txt
bahnbusiness.egg-info/dependency_links.txt
bahnbusiness.egg-info/requires.txt
bahnbusiness.egg-info/top_level.txt
bahnbusiness.egg-info/zip-safe
test/test_bahnapi.py