Metadata-Version: 1.1
Name: bahnbusiness
Version: 1.0.0
Summary: Scrape the bahn.de business website for tickets and other information.
Home-page: https://github.com/uberspace/bahnbusiness
Author: uberspace.de
Author-email: hallo@uberspace.de
License: MIT
Platform: UNKNOWN
Classifier: Development Status :: 3 - Alpha
Classifier: Intended Audience :: Information Technology
Classifier: Intended Audience :: Developers
Classifier: Topic :: Office/Business
Classifier: Topic :: Utilities
Classifier: Natural Language :: English
Classifier: Operating System :: POSIX :: Linux
Classifier: License :: OSI Approved :: MIT License
Classifier: Programming Language :: Python :: Implementation :: CPython
Classifier: Programming Language :: Python :: 3.6
